CHANGES.rst
CONTRIBUTORS.rst
DEVELOP.rst
LICENSE.rst
MANIFEST.in
README.rst
setup.cfg
setup.py
docs/conf.py
docs/index.rst
src/collective/__init__.py
src/collective.easyformplugin.createdx.egg-info/PKG-INFO
src/collective.easyformplugin.createdx.egg-info/SOURCES.txt
src/collective.easyformplugin.createdx.egg-info/dependency_links.txt
src/collective.easyformplugin.createdx.egg-info/entry_points.txt
src/collective.easyformplugin.createdx.egg-info/namespace_packages.txt
src/collective.easyformplugin.createdx.egg-info/not-zip-safe
src/collective.easyformplugin.createdx.egg-info/requires.txt
src/collective.easyformplugin.createdx.egg-info/top_level.txt
src/collective/easyformplugin/__init__.py
src/collective/easyformplugin/createdx/__init__.py
src/collective/easyformplugin/createdx/actions.py
src/collective/easyformplugin/createdx/actions.zcml
src/collective/easyformplugin/createdx/configure.zcml
src/collective/easyformplugin/createdx/interfaces.py
src/collective/easyformplugin/createdx/permissions.zcml
src/collective/easyformplugin/createdx/setuphandlers.py
src/collective/easyformplugin/createdx/testing.py
src/collective/easyformplugin/createdx/upgrades.py
src/collective/easyformplugin/createdx/upgrades.zcml
src/collective/easyformplugin/createdx/locales/README.rst
src/collective/easyformplugin/createdx/locales/__init__.py
src/collective/easyformplugin/createdx/locales/collective.easyformplugin.createdx.pot
src/collective/easyformplugin/createdx/locales/update.py
src/collective/easyformplugin/createdx/locales/update.sh
src/collective/easyformplugin/createdx/locales/en/LC_MESSAGES/collective.easyformplugin.createdx.po
src/collective/easyformplugin/createdx/profiles/default/catalog.xml
src/collective/easyformplugin/createdx/profiles/default/metadata.xml
src/collective/easyformplugin/createdx/profiles/default/registry.xml
src/collective/easyformplugin/createdx/profiles/default/rolemap.xml
src/collective/easyformplugin/createdx/tests/__init__.py
src/collective/easyformplugin/createdx/tests/test_robot.py
src/collective/easyformplugin/createdx/tests/test_setup.py
src/collective/easyformplugin/createdx/tests/robot/test_example.robot