Metadata-Version: 2.1
Name: collective.easyformplugin.createdx
Version: 1.0a3
Summary: Create dexterity objects from easyform submissions
Home-page: https://github.com/collective/collective.easyformplugin.createdx
Author: Peter Holzer
Author-email: peter.holzer@agitator.com
License: GPL version 2
Project-URL: PyPI, https://pypi.python.org/pypi/collective.easyformplugin.createdx
Project-URL: Source, https://github.com/collective/collective.easyformplugin.createdx
Project-URL: Tracker, https://github.com/collective/collective.easyformplugin.createdx/issues
Keywords: Python Plone
Platform: UNKNOWN
Classifier: Environment :: Web Environment
Classifier: Framework :: Plone
Classifier: Framework :: Plone :: Addon
Classifier: Framework :: Plone :: 5.1
Classifier: Framework :: Plone :: 5.2
Classifier: Programming Language :: Python
Classifier: Programming Language :: Python :: 2.7
Classifier: Programming Language :: Python :: 3.6
Classifier: Programming Language :: Python :: 3.7
Classifier: Operating System :: OS Independent
Classifier: License :: OSI Approved :: GNU General Public License v2 (GPLv2)
Requires-Python: ==2.7, >=3.6
Provides-Extra: test
